fs_store_cli/__init__.py
fs_store_cli/cli.py
fs_store_cli-1.3.dist-info/METADATA
fs_store_cli-1.3.dist-info/RECORD
fs_store_cli-1.3.dist-info/WHEEL
fs_store_cli-1.3.dist-info/entry_points.txt
fs_store_cli-1.3.dist-info/top_level.txt
