Metadata-Version: 2.1
Name: fs-store-cli
Version: 1.3
Summary: A CLI tool to interact with the file server
Home-page: UNKNOWN
Author: Gajendra Waghmare
Author-email: gajendraw1237@gmail.com
License: proprietary
Platform: UNKNOWN
Classifier: Programming Language :: Python :: 3
Classifier: License :: OSI Approved :: MIT License
Classifier: Operating System :: OS Independent
Requires-Python: >=3.6
Requires-Dist: click
Requires-Dist: requests
